pyvlq/__init__.py
pyvlq/core.py
pyvlq/py.typed
pyvlq-0.1.1.dist-info/LICENSE
pyvlq-0.1.1.dist-info/WHEEL
pyvlq-0.1.1.dist-info/METADATA
pyvlq-0.1.1.dist-info/RECORD
